{
  "word": "blueprints",
  "pronunciation": "bloo·prints",
  "concise_definition": "n. 蓝图, 设计图, 计划",
  "forms": {
    "singular": "blueprint"
  },
  "definitions": [
    {
      "pos": "noun",
      "explanation_en": "A detailed technical drawing or plan, especially for buildings, machines, or systems, showing dimensions, materials, and construction methods.",
      "explanation_cn": "指用于建筑、机器或系统等的详细技术图纸，标明尺寸、材料和施工方法。",
      "example_en": "The architects reviewed the blueprints before beginning construction.",
      "example_cn": "建筑师在开工前审查了蓝图。"
    },
    {
      "pos": "noun",
      "explanation_en": "A detailed plan or model for achieving a goal, often used metaphorically to describe a strategy or framework.",
      "explanation_cn": "指为实现某一目标而制定的详细计划或模型，常用于比喻性地描述策略或框架。",
      "example_en": "The government released a blueprint for improving public education.",
      "example_cn": "政府发布了一份改善公共教育的行动计划。"
    }
  ],
  "comparison": [
    {
      "word_to_compare": "plan",
      "analysis": "“Plan”（计划）是一个更广泛、更通用的词，泛指任何为达成目标而制定的步骤或安排，可以是口头的、简略的或非正式的。而 “blueprint” 强调的是结构完整、细节精确、具有可执行性的系统性方案，常带有技术性或官方性。"
    },
    {
      "word_to_compare": "design",
      "analysis": "“Design”（设计）侧重于外观、功能或美学上的构思，强调创意和形式，不一定包含实施细节。而 “blueprint” 更注重可操作性，包含具体尺寸、材料、流程等执行层面的信息，是设计的落地版本。"
    },
    {
      "word_to_compare": "scheme",
      "analysis": "“Scheme”（方案）常指一种有组织的计划，但有时带有负面含义（如阴谋或诡计），且不一定具有技术性或可视化特征。而 “blueprint” 是中性或正面的术语，强调清晰、系统、可复制的结构，常用于工程、建筑或政策领域。"
    }
  ]
}