{
  "word": "buys",
  "pronunciation": "bīz",
  "concise_definition": "v. 购买（buy 的第三人称单数形式）",
  "forms": {
    "base_form": "buy",
    "past_tense": "bought",
    "past_participle": "bought",
    "present_participle": "buying",
    "plural": "buys"
  },
  "definitions": [
    {
      "pos": "verb",
      "explanation_en": "To acquire something in exchange for money or other value; to purchase.",
      "explanation_cn": "指以金钱或其他价值换取某物；购买。",
      "example_en": "She buys groceries every Saturday morning.",
      "example_cn": "她每周六早上都去买杂货。"
    },
    {
      "pos": "verb",
      "explanation_en": "To accept or believe something, often reluctantly or without critical evaluation (informal usage).",
      "explanation_cn": "（非正式用法）指接受或相信某事，常带有勉强或未经深思熟虑的意味。",
      "example_en": "I don't buy that excuse—he was clearly lying.",
      "example_cn": "我不信这个借口——他明显在撒谎。"
    }
  ],
  "comparison": [
    {
      "word_to_compare": "purchases",
      "analysis": "“Purchases” 是 “buy” 的名词形式，强调购买的行为或结果（如购物清单、交易记录），而 “buys” 是动词的第三人称单数形式，强调动作本身。两者词性不同，不能直接互换，但在语义上高度相关。"
    },
    {
      "word_to_compare": "acquires",
      "analysis": "“Acquires” (获得) 比 “buys” 更广泛，可指通过任何方式获得，包括继承、赠送、交换或购买。而 “buys” 特指通过支付金钱获得，具有明确的交易属性。"
    },
    {
      "word_to_compare": "gets",
      "analysis": "“Gets” (得到) 是最口语化、最泛化的词，可表示通过购买、索取、发现、接受等方式获得某物，语义模糊。而 “buys” 明确指向金钱交易，语义更精确。"
    }
  ]
}