{
  "word": "cemeteries",
  "pronunciation": "seh·muh·teer·eez",
  "concise_definition": "n. 墓地, 公墓",
  "forms": {
    "singular": "cemetery"
  },
  "definitions": [
    {
      "pos": "noun",
      "explanation_en": "A designated area of land where the dead are buried or their remains interred, often including graves, headstones, and memorial structures, and sometimes maintained as a place of quiet reflection.",
      "explanation_cn": "指专门用于安葬死者或存放遗骸的土地区域，通常包括坟墓、墓碑和纪念设施，有时也被维护为供人静思缅怀的场所。",
      "example_en": "The old cemetery on the hill is filled with gravestones from the 18th century.",
      "example_cn": "山上的那座古老墓地里满是18世纪的墓碑。"
    },
    {
      "pos": "noun",
      "explanation_en": "A place where memories of the deceased are preserved and honored, often serving as a cultural or historical site reflecting community values and burial traditions.",
      "explanation_cn": "指保存和纪念逝者记忆的地方，常作为反映社区价值观和丧葬传统的文化或历史遗址。",
      "example_en": "Visitors come to the national cemetery to pay respects to fallen soldiers.",
      "example_cn": "游客来到国家公墓，向阵亡将士致以敬意。"
    }
  ],
  "comparison": [
    {
      "word_to_compare": "graveyard",
      "analysis": "“Graveyard” (墓地) 是 “cemetery” 的非正式同义词，通常指较小、较古老的墓地，常与教堂相连，带有更朴素或乡土的气息。而 “cemetery” 更正式、更广泛，可指任何规模的公共或私人安葬地，包括现代大型公墓。"
    },
    {
      "word_to_compare": "burial ground",
      "analysis": "“Burial ground” (安葬地) 是一个更中性、更描述性的术语，强调其功能——用于埋葬死者，不带文化或情感色彩。它常用于历史或考古语境，而 “cemetery” 则隐含了纪念、维护和仪式性。"
    },
    {
      "word_to_compare": "mausoleum",
      "analysis": "“Mausoleum” (陵墓) 指为单个或少数人建造的大型、独立的石制纪念建筑，通常用于重要人物，如统治者或名人。它是一种具体的安葬结构，而 “cemetery” 是包含多个墓穴的广阔区域。"
    }
  ]
}