{
  "word": "crumbling",
  "pronunciation": "kruhm·blihng",
  "concise_definition": "adj. 崩塌的, 崩解的, 衰败的; v. 崩塌, 崩解, 衰败",
  "forms": {
    "base_form": "crumble",
    "third_person_singular": "crumbles",
    "past_tense": "crumbled",
    "past_participle": "crumbled",
    "present_participle": "crumbling"
  },
  "definitions": [
    {
      "pos": "verb",
      "explanation_en": "To break apart gradually into small pieces, often due to age, decay, or pressure; to fall into disrepair or decline.",
      "explanation_cn": "指因年久、腐朽或压力而逐渐碎裂成小块；也指逐渐失修或走向衰败。",
      "example_en": "The ancient castle walls are crumbling after centuries of exposure to the elements.",
      "example_cn": "这座古堡的墙壁在经历数个世纪的风吹雨打后已开始崩解。"
    },
    {
      "pos": "verb",
      "explanation_en": "To deteriorate or fail gradually, especially in terms of authority, structure, or stability.",
      "explanation_cn": "指（权威、结构或稳定性）逐渐恶化或崩溃，常用于抽象概念。",
      "example_en": "Public trust in the institution is crumbling under the weight of corruption scandals.",
      "example_cn": "在腐败丑闻的重压下，公众对该机构的信任正在瓦解。"
    },
    {
      "pos": "adjective",
      "explanation_en": "In the process of breaking apart or falling into decay; describing something that is fragile, worn, or deteriorating.",
      "explanation_cn": "处于碎裂或腐朽过程中的状态；形容某物脆弱、陈旧或正在衰败。",
      "example_en": "They walked through the crumbling ruins of the forgotten temple.",
      "example_cn": "他们走过那座被遗忘神庙的残垣断壁。"
    }
  ],
  "comparison": [
    {
      "word_to_compare": "collapsing",
      "analysis": "“Collapsing” (坍塌) 指突然、迅速的结构性崩溃，通常伴随明显的物理或系统性失败，如建筑物倒塌或经济体系崩溃。而 “crumbling” 强调缓慢、渐进的分解过程，更侧重于时间累积导致的瓦解，而非突发性事件。"
    },
    {
      "word_to_compare": "decaying",
      "analysis": "“Decaying” (腐烂/衰败) 主要用于有机物的生物性分解，如食物腐烂或尸体腐败，强调化学或生物过程。而 “crumbling” 更广泛用于物理结构的碎裂，也可用于抽象事物（如制度、信任），其焦点是形态的破碎而非化学变化。"
    },
    {
      "word_to_compare": "eroding",
      "analysis": "“Eroding” (侵蚀) 通常指由外力（如风、水）持续作用导致的物质逐渐流失，常用于自然地理语境（如海岸侵蚀）。虽然也表示渐进性损失，但 “eroding” 更强调外部力量的作用，而 “crumbling” 更强调内部结构的失效或老化。"
    }
  ]
}