{
  "word": "curled",
  "pronunciation": "kurld",
  "concise_definition": "adj. 卷曲的, 蜷曲的; v. 卷曲（curl 的过去式和过去分词）",
  "forms": {
    "base_form": "curl",
    "present_participle": "curling",
    "third_person_singular": "curls",
    "past_tense": "curled",
    "past_participle": "curled"
  },
  "definitions": [
    {
      "pos": "adjective",
      "explanation_en": "Having a bent or twisted shape, especially in a spiral or rounded form, often describing hair, paper, or edges that are not straight.",
      "explanation_cn": "呈弯曲或扭转形状的，尤其指呈螺旋状或圆形的，常用于描述头发、纸张或边缘不平直的状态。",
      "example_en": "She had long, golden curled hair that fell softly over her shoulders.",
      "example_cn": "她有一头长长的金色卷发，轻轻垂落在肩膀上。"
    },
    {
      "pos": "adjective",
      "explanation_en": "Describing something that is folded or bent inward, such as leaves or fingers, often due to cold, age, or natural form.",
      "explanation_cn": "形容某物向内折叠或弯曲，如叶子或手指，常因寒冷、年老或自然形态所致。",
      "example_en": "The old man’s fingers were curled tightly around the walking stick.",
      "example_cn": "老人的手指紧紧蜷曲在拐杖上。"
    },
    {
      "pos": "verb",
      "explanation_en": "To form or cause something to form into a curved or spiral shape, often by twisting or rolling.",
      "explanation_cn": "使某物形成或导致某物形成弯曲或螺旋状的形状，通常通过扭转或卷绕实现。",
      "example_en": "The smoke curled upward from the chimney in thin spirals.",
      "example_cn": "烟从烟囱中袅袅升起，形成细小的螺旋。"
    }
  ],
  "comparison": [
    {
      "word_to_compare": "curved",
      "analysis": "“Curved”（弯曲的）泛指任何非直线的形状，可以是平滑的弧线，不一定有卷绕或螺旋的特征。而 “curled” 强调的是卷曲、盘绕或向内折叠的形态，通常带有更明显的旋转或缠绕感，如卷发或卷起的纸片。"
    },
    {
      "word_to_compare": "twisted",
      "analysis": "“Twisted”（扭曲的）强调因外力导致的不自然、甚至变形的弯曲，常带有负面含义（如扭曲事实、扭伤）。而 “curled” 更多描述自然、柔和或美观的卷曲状态，如卷发或卷叶，不隐含损伤或变形。"
    },
    {
      "word_to_compare": "coiled",
      "analysis": "“Coiled”（盘绕的）通常指有规律地一圈圈缠绕，如蛇盘绕或电线缠绕，强调结构的紧密和重复性。而 “curled” 可以是单次、松散或不规则的卷曲，不一定形成完整环状，更常用于描述柔软物体的自然形态。"
    }
  ]
}