{
  "word": "cutie",
  "pronunciation": "koo·tee",
  "concise_definition": "n. 可爱的人, 小可爱, 惹人喜爱的人",
  "forms": {
    "plural": "cuties"
  },
  "definitions": [
    {
      "pos": "noun",
      "explanation_en": "A colloquial and affectionate term used to describe someone who is charmingly attractive, often in a youthful, innocent, or endearing way; commonly used to refer to children, pets, or romantic partners.",
      "explanation_cn": "一个口语化且充满爱意的术语，用于形容某人具有迷人吸引力，通常带有年轻、纯真或惹人怜爱的特质；常用于指儿童、宠物或恋人。",
      "example_en": "Look at that little puppy—what a cutie!",
      "example_cn": "看看那只小狗——多可爱啊！"
    },
    {
      "pos": "noun",
      "explanation_en": "A term of endearment in pop culture or romantic contexts, often used playfully or flirtatiously to express admiration for someone’s appearance or demeanor.",
      "explanation_cn": "在流行文化或浪漫语境中用作亲昵称呼，常以轻松或调情的方式表达对某人外貌或举止的欣赏。",
      "example_en": "She walked into the room and everyone called her a cutie for her sweet smile.",
      "example_cn": "她走进房间，因为甜美的微笑，大家都叫她小可爱。"
    }
  ],
  "comparison": [
    {
      "word_to_compare": "cutie",
      "analysis": "“Cutie” 是一个非正式、情感色彩浓厚的词，强调外貌或气质上的可爱，常用于亲密或轻松的语境，带有主观喜爱的意味。它比 “beautiful” 或 “attractive” 更轻盈、更童真，且不强调成熟魅力。"
    },
    {
      "word_to_compare": "charmer",
      "analysis": "“Charmer” (有魅力的人) 指通过举止、言谈或个性吸引他人的人，侧重于社交魅力和影响力，可能带有策略性或操纵性。而 “cutie” 更强调无意识的、自然流露的可爱，通常不涉及主动吸引的行为。"
    },
    {
      "word_to_compare": "sweetheart",
      "analysis": "“Sweetheart” (亲爱的) 是一种更广泛、更深情的爱称，可用于表达亲密关系中的情感依恋，不限于外貌。而 “cutie” 更聚焦于视觉或行为上的可爱特质，情感深度较浅，常用于调侃或短暂的赞美。"
    }
  ]
}