{
  "word": "defines",
  "pronunciation": "dih·fahynz",
  "concise_definition": "v. 定义, 说明, 界定",
  "forms": {
    "third_person_singular": "defines",
    "past_tense": "defined",
    "past_participle": "defined",
    "present_participle": "defining"
  },
  "definitions": [
    {
      "pos": "verb",
      "explanation_en": "To state the exact meaning of a word, term, or concept, typically in a clear and precise manner to eliminate ambiguity.",
      "explanation_cn": "以清晰、精确的方式陈述一个词、术语或概念的确切含义，以消除歧义。",
      "example_en": "The dictionary defines 'honesty' as 'the quality of being truthful and sincere.'",
      "example_cn": "词典将‘诚实’定义为‘真实和真诚的品质’。"
    },
    {
      "pos": "verb",
      "explanation_en": "To establish or set the boundaries, limits, or characteristics of something, often to clarify its scope or nature.",
      "explanation_cn": "确立或设定某事物的边界、限制或特征，通常用于明确其范围或性质。",
      "example_en": "The law defines the rights and responsibilities of citizens.",
      "example_cn": "法律界定了公民的权利与责任。"
    },
    {
      "pos": "verb",
      "explanation_en": "To shape or determine the essential nature or identity of something, often through influence or context.",
      "explanation_cn": "通过影响或背景塑造或决定某事物的本质或身份。",
      "example_en": "Her childhood experiences defined her worldview.",
      "example_cn": "她的童年经历塑造了她的世界观。"
    }
  ],
  "comparison": [
    {
      "word_to_compare": "describe",
      "analysis": "“Describe” (描述) 侧重于用语言呈现事物的外观、特征或过程，强调细节和感官印象，但不一定明确其本质或边界。而 “define” 更注重精确界定含义或范围，具有规范性和排他性。"
    },
    {
      "word_to_compare": "explain",
      "analysis": "“Explain” (解释) 的目的是使复杂或模糊的事物变得容易理解，常包含原因、过程或背景。它更注重逻辑和因果关系。而 “define” 仅聚焦于给出明确的含义或界限，不涉及推导或论证。"
    },
    {
      "word_to_compare": "determine",
      "analysis": "“Determine” (决定/确定) 强调通过判断、分析或权威手段得出结论或结果，常用于决策或因果关系。而 “define” 更侧重于语言或概念上的清晰化，不必然涉及判断或强制性结果。"
    }
  ]
}