{
  "word": "eliminates",
  "pronunciation": "ih·lim·uh·neyt",
  "concise_definition": "v. 消除, 排除, 根除",
  "forms": {
    "base_form": "eliminate",
    "third_person_singular": "eliminates",
    "past_tense": "eliminated",
    "past_participle": "eliminated",
    "present_participle": "eliminating"
  },
  "definitions": [
    {
      "pos": "verb",
      "explanation_en": "To remove or get rid of something completely, especially something unwanted, harmful, or unnecessary, often through deliberate action.",
      "explanation_cn": "指通过有意识的行动彻底移除或消除某物，尤其是那些不想要的、有害的或不必要的事物。",
      "example_en": "The new policy eliminates all unnecessary bureaucracy in the department.",
      "example_cn": "这项新政策消除了部门内所有不必要的官僚程序。"
    },
    {
      "pos": "verb",
      "explanation_en": "To remove someone or something from competition, consideration, or existence, often in a decisive or final manner.",
      "explanation_cn": "指将某人或某物从竞争、考虑范围或存在中彻底剔除，通常以决定性或最终的方式进行。",
      "example_en": "The defending champion was eliminated in the first round of the tournament.",
      "example_cn": "卫冕冠军在第一轮比赛中就被淘汰了。"
    },
    {
      "pos": "verb",
      "explanation_en": "To cause something to cease to exist or function, especially by removing its basis or source.",
      "explanation_cn": "指通过移除其基础或来源，使某事物停止存在或运作。",
      "example_en": "The antibiotic eliminates the bacteria causing the infection.",
      "example_cn": "这种抗生素杀灭了导致感染的细菌。"
    }
  ],
  "comparison": [
    {
      "word_to_compare": "removes",
      "analysis": "“Removes” (移除) 指将某物从某个位置或情境中拿走，但不一定意味着彻底终结或根除。它更侧重于物理或空间上的转移。而 “eliminates” 强调彻底清除，常带有终结性或功能性上的灭除，语义更强。"
    },
    {
      "word_to_compare": "eradicates",
      "analysis": "“Eradicates” (根除) 与 “eliminates” 非常接近，但更强调彻底、永久地消灭，尤其用于疾病、有害制度或物种等严重问题。它带有更强的科学或系统性语境，而 “eliminates” 使用范围更广，可适用于日常或抽象情境。"
    },
    {
      "word_to_compare": "excludes",
      "analysis": "“Excludes” (排除) 指将某人或某物挡在某个群体、过程或范围之外，但不意味着其本身被消灭或终止。它强调的是准入的拒绝，而非存在的终结。而 “eliminates” 意味着该事物被彻底清除，不再存在或起作用。"
    }
  ]
}