{
  "word": "estimation",
  "pronunciation": "es·tuh·mey·shun",
  "concise_definition": "n. 估计, 估算, 评价",
  "forms": {
    "plural": "estimations"
  },
  "definitions": [
    {
      "pos": "noun",
      "explanation_en": "An approximate calculation or judgment of the value, number, quantity, or extent of something, often based on incomplete information.",
      "explanation_cn": "指基于不完整信息对某事物的价值、数量、规模或程度所作的近似计算或判断。",
      "example_en": "The engineer gave an estimation of the project's cost at $500,000.",
      "example_cn": "工程师对该项目的成本估算为50万美元。"
    },
    {
      "pos": "noun",
      "explanation_en": "A personal opinion or judgment about someone's character, abilities, or worth, often reflecting admiration or respect.",
      "explanation_cn": "指对某人品格、能力或价值的个人看法或评价，常带有钦佩或尊重的意味。",
      "example_en": "She has a high estimation of her mentor's wisdom and integrity.",
      "example_cn": "她对导师的智慧与正直评价很高。"
    }
  ],
  "comparison": [
    {
      "word_to_compare": "estimate",
      "analysis": "“Estimate” 是动词或名词，指具体的估算行为或结果，更常用于数学、工程或财务等量化语境。而 “estimation” 作为名词时，更侧重于抽象的评价或总体判断，尤其在表达主观看法时更正式、更书面化。"
    },
    {
      "word_to_compare": "assessment",
      "analysis": "“Assessment” (评估) 通常指系统性、有标准的分析过程，常用于教育、绩效或风险领域，强调客观性和程序性。而 “estimation” 更偏向于快速、粗略的判断，不一定基于严谨方法。"
    },
    {
      "word_to_compare": "appraisal",
      "analysis": "“Appraisal” (估价/评价) 多用于专业领域，如房地产、艺术品或员工绩效，强调权威性、正式性和结论性。而 “estimation” 可以是随意的、非正式的，且不一定具有权威性。"
    }
  ]
}