{
  "word": "exited",
  "pronunciation": "ik·sīt·id",
  "concise_definition": "v. 离开, 退出 (exit 的过去式和过去分词)",
  "forms": {
    "base_form": "exit",
    "third_person_singular": "exits",
    "present_participle": "exiting",
    "past_tense": "exited",
    "past_participle": "exited"
  },
  "definitions": [
    {
      "pos": "verb",
      "explanation_en": "To leave a place, especially a building, room, vehicle, or organized event, often formally or deliberately.",
      "explanation_cn": "指离开某个场所，尤其是建筑物、房间、车辆或有组织的活动，通常带有正式或有意的意味。",
      "example_en": "The audience exited the theater quietly after the performance ended.",
      "example_cn": "演出结束后，观众安静地离开了剧院。"
    },
    {
      "pos": "verb",
      "explanation_en": "To leave a position, organization, or system, such as a job, political party, or relationship.",
      "explanation_cn": "指退出某个职位、组织或体系，如工作、政党或关系。",
      "example_en": "She exited the company after ten years of service to pursue her own startup.",
      "example_cn": "她在公司服务十年后离职，去创办自己的初创企业。"
    },
    {
      "pos": "verb",
      "explanation_en": "In computing or gaming, to terminate a session or leave a program or environment.",
      "explanation_cn": "在计算机或游戏语境中，指终止会话或退出程序或环境。",
      "example_en": "He exited the app without saving his progress.",
      "example_cn": "他退出应用程序时没有保存进度。"
    }
  ],
  "comparison": [
    {
      "word_to_compare": "leave",
      "analysis": "“Leave” (离开) 是最通用的词，适用于任何情境下的离开，不强调方式或正式性。而 “exited” 更常用于指从特定场所、系统或组织中正式或有意识地离开，语义范围更窄，语境更具体。"
    },
    {
      "word_to_compare": "depart",
      "analysis": "“Depart” (启程/离开) 比 “exited” 更正式，常用于书面语或重大场合，如航班、船只、军队的离开，带有仪式感或长途移动的意味。而 “exited” 更常用于日常或物理空间的离开，如房间、建筑。"
    },
    {
      "word_to_compare": "quit",
      "analysis": "“Quit” (辞去/停止) 强调主动终止某种责任、习惯或状态，常带有负面或决绝的语气，如 quit smoking 或 quit a job。而 “exited” 更中性，仅描述离开的动作，不隐含情绪或评价。"
    }
  ]
}