{
  "word": "managed",
  "pronunciation": "man·ijd",
  "concise_definition": "v. 管理, 控制, 设法完成",
  "forms": {
    "base_form": "manage",
    "third_person_singular": "manages",
    "past_tense": "managed",
    "past_participle": "managed",
    "present_participle": "managing"
  },
  "definitions": [
    {
      "pos": "verb",
      "explanation_en": "To be in charge of or direct the operation, affairs, or personnel of an organization, project, or system, often with responsibility for planning, organizing, and decision-making.",
      "explanation_cn": "负责指挥、监督某个组织、项目或系统的运作、事务或人员，通常包括计划、组织和决策的责任。",
      "example_en": "She managed the team effectively, ensuring all deadlines were met.",
      "example_cn": "她有效地管理了团队，确保所有截止日期都按时完成。"
    },
    {
      "pos": "verb",
      "explanation_en": "To succeed in dealing with or accomplishing something difficult or challenging, often with limited resources or under pressure.",
      "explanation_cn": "指在资源有限或压力下，设法完成某件困难或具有挑战性的事情。",
      "example_en": "Despite the budget cuts, they managed to finish the project on time.",
      "example_cn": "尽管预算被削减，他们还是设法按时完成了项目。"
    },
    {
      "pos": "verb",
      "explanation_en": "To handle or control something physically or mechanically, especially with skill or care.",
      "explanation_cn": "指以技巧或谨慎的方式操作或控制某物，尤指物理或机械层面的操控。",
      "example_en": "He managed the steering wheel with one hand while talking on the phone.",
      "example_cn": "他一边打电话，一边单手操控方向盘。"
    }
  ],
  "comparison": [
    {
      "word_to_compare": "administer",
      "analysis": "“Administer”（管理/执行）更侧重于执行规则、政策或官方事务，常用于政府、法律或医疗语境，强调程序性和规范性。而 “managed” 更广泛，涵盖领导、协调和实际操作，适用范围更广。"
    },
    {
      "word_to_compare": "control",
      "analysis": "“Control”（控制）强调对人或事物施加直接的支配或限制，有时带有强制性；而 “managed” 更强调通过组织、协调和引导达成目标，通常隐含更积极、建设性的含义。"
    },
    {
      "word_to_compare": "handle",
      "analysis": "“Handle”（处理）语气更口语化，常用于描述应对具体任务或突发状况，强调能力而非系统性领导；而 “managed” 更正式，常用于描述长期、有结构的职责履行，尤其在组织或项目层面。"
    }
  ]
}