{
  "word": "medalist",
  "pronunciation": "meh·duh·list",
  "concise_definition": "n. 获奖者, 获得奖牌者",
  "forms": {
    "plural": "medalists"
  },
  "definitions": [
    {
      "pos": "noun",
      "explanation_en": "A person who has won a medal in a competitive event, especially in sports such as the Olympics, World Championships, or other official contests.",
      "explanation_cn": "指在竞技活动中赢得奖牌的人，尤指在奥运会、世界锦标赛或其他官方赛事中获得奖牌的运动员。",
      "example_en": "The young swimmer became a medalist after winning gold in the 100-meter freestyle.",
      "example_cn": "这位年轻游泳运动员在100米自由泳中夺得金牌，成为奖牌得主。"
    },
    {
      "pos": "noun",
      "explanation_en": "Someone recognized for outstanding achievement in a field, often symbolized by receiving a medal as an honor or award.",
      "explanation_cn": "指因在某一领域取得卓越成就而被授予奖牌以示表彰的人，奖牌常作为荣誉的象征。",
      "example_en": "She is a medalist in both science and literature, honored for her groundbreaking research and poetry.",
      "example_cn": "她在科学和文学领域均获殊荣，因其开创性的研究和诗歌作品而被授予奖牌。"
    }
  ],
  "comparison": [
    {
      "word_to_compare": "champion",
      "analysis": "“Champion”（冠军）特指在比赛中获得第一名的选手，强调最高荣誉和胜利；而 “medalist”（奖牌得主）范围更广，包括获得金、银、铜牌的所有人，不一定是最优者。一个冠军一定是奖牌得主，但奖牌得主不一定是冠军。"
    },
    {
      "word_to_compare": "winner",
      "analysis": "“Winner”（获胜者）泛指任何比赛或竞赛中的胜出者，可能没有奖牌，也可能仅获奖状或奖杯；而 “medalist” 专指获得实体奖牌的人，通常用于正式体育赛事，语义更具体、更制度化。"
    },
    {
      "word_to_compare": "award recipient",
      "analysis": "“Award recipient”（获奖者）是一个更宽泛的术语，涵盖所有获得任何形式奖励的人，如证书、奖金、奖杯等；而 “medalist” 仅限于获得奖牌者，具有明确的物质形式和体育/竞赛语境，使用范围更窄但更精准。"
    }
  ]
}