{
  "word": "migrants",
  "pronunciation": "mahy·grents",
  "concise_definition": "n. 移民, 迁移者, 流动人口",
  "forms": {
    "singular": "migrant"
  },
  "definitions": [
    {
      "pos": "noun",
      "explanation_en": "A person who moves from one place to another, typically across international borders or within a country, in search of better living conditions, employment, or safety.",
      "explanation_cn": "指为寻求更好的生活条件、就业机会或安全保障而从一个地方迁移到另一个地方的人，通常涉及跨国或国内迁移。",
      "example_en": "Many migrants flee war-torn regions to seek refuge in neighboring countries.",
      "example_cn": "许多移民逃离战乱地区，前往邻国寻求庇护。"
    },
    {
      "pos": "noun",
      "explanation_en": "A person who moves seasonally or periodically to work in agriculture, construction, or other labor-intensive industries, often returning to their home region after the work season ends.",
      "explanation_cn": "指为从事农业、建筑或其他劳动密集型行业而季节性或周期性迁移的人，通常在工作季节结束后返回家乡。",
      "example_en": "Seasonal migrants travel from rural areas to cities each spring to work in the harvest.",
      "example_cn": "季节性移民每年春天从农村前往城市参与收割工作。"
    }
  ],
  "comparison": [
    {
      "word_to_compare": "immigrants",
      "analysis": "“Immigrants”（移民）特指永久性迁移到另一个国家并意图定居的人，强调长期居住和身份转变；而 “migrants” 是更广泛的术语，涵盖短期、季节性或临时性迁移者，不一定有定居意图。"
    },
    {
      "word_to_compare": "refugees",
      "analysis": "“Refugees”（难民）是因战争、迫害或灾难而被迫逃离家园的人，其迁移具有法律保护的特殊地位；而 “migrants” 通常是出于经济或生活改善的主动选择，不必然面临生命威胁。"
    },
    {
      "word_to_compare": "expatriates",
      "analysis": "“Expatriates”（外派人员/侨民）通常指因工作或个人原因自愿长期居住在国外的本国公民，常带有中性或积极的社会经济背景；而 “migrants” 更常用于描述经济弱势或处境艰难的流动人口，语义上更具社会关怀色彩。"
    }
  ]
}