{
  "word": "mustang",
  "pronunciation": "mus·tang",
  "concise_definition": "n. 野马, 福特野马汽车",
  "forms": {
    "plural": "mustangs"
  },
  "definitions": [
    {
      "pos": "noun",
      "explanation_en": "A free-roaming, wild horse of the North American West, descended from domesticated horses brought by Spanish explorers; known for its hardiness, speed, and independent spirit.",
      "explanation_cn": "指生活在北美西部的野生马，源自西班牙探险家带来的家马；以坚韧、迅捷和独立不羁的特性著称。",
      "example_en": "The mustangs roam freely across the open plains of Nevada.",
      "example_cn": "野马在内华达州的辽阔平原上自由驰骋。"
    },
    {
      "pos": "noun",
      "explanation_en": "A popular model of sports car produced by Ford since 1964, known for its powerful engine, sleek design, and iconic status in American automotive culture.",
      "explanation_cn": "指福特自1964年以来生产的著名跑车型号，以其强劲引擎、流线造型和在美国汽车文化中的标志性地位而闻名。",
      "example_en": "He saved for years to buy his dream car: a 1967 Ford Mustang.",
      "example_cn": "他攒了多年钱，只为买下梦想中的座驾：一辆1967年的福特野马。"
    }
  ],
  "comparison": [
    {
      "word_to_compare": "horse",
      "analysis": "“Horse”（马）是泛指所有马类动物的总称，包括家养马、赛马、工作马等，是一个广泛而中性的词。而 “mustang” 特指北美野生的、具有特定血统和历史背景的野马，带有文化与自然野性的独特内涵。"
    },
    {
      "word_to_compare": "pony",
      "analysis": "“Pony”（小马）指体型较小的马种，通常肩高低于14.2手（约1.47米），多用于儿童骑乘或特定工作。而 “mustang” 并不以体型定义，而是以野生状态和血统为特征，其体型通常与普通马无异，甚至更大更强壮。"
    },
    {
      "word_to_compare": "coupe",
      "analysis": "“Coupe”（双门轿跑车）是一个车身结构分类术语，指拥有两个车门和固定车顶的紧凑型轿车。而 “Mustang” 是一个具体品牌车型名称，虽然它常采用coupe设计，但其文化象征意义远超结构定义，代表美式肌肉车精神与自由个性。"
    }
  ]
}