{
  "word": "pennies",
  "pronunciation": "pen·iz",
  "concise_definition": "n. 分（美分）, 零钱, 微不足道的钱",
  "forms": {
    "singular": "penny"
  },
  "definitions": [
    {
      "pos": "noun",
      "explanation_en": "The smallest unit of currency in several countries, including the United States and the United Kingdom, worth one-hundredth of a dollar or one-hundredth of a pound.",
      "explanation_cn": "美国和英国等国家的最小货币单位，等于一美元或一英镑的百分之一。",
      "example_en": "She saved every penny she earned to buy a new bike.",
      "example_cn": "她把赚到的每一分钱都存起来，以便买一辆新自行车。"
    },
    {
      "pos": "noun",
      "explanation_en": "A very small amount of money, often used to emphasize insignificance or poverty.",
      "explanation_cn": "指极少的钱，常用于强调金额微不足道或经济拮据。",
      "example_en": "He doesn't have pennies to his name — he's completely broke.",
      "example_cn": "他身无分文，穷得叮当响。"
    },
    {
      "pos": "noun",
      "explanation_en": "Used in plural form to refer to multiple coins of low value, often in a casual or idiomatic context.",
      "explanation_cn": "复数形式常用于口语或习语中，泛指多个低价值的硬币，带有生活化或比喻色彩。",
      "example_en": "I found a few pennies rattling around in the bottom of my purse.",
      "example_cn": "我在钱包底部找到了几枚叮当作响的硬币。"
    }
  ],
  "comparison": [
    {
      "word_to_compare": "cents",
      "analysis": "“Cents” 是美式英语中对“分”的标准说法，与 “pennies” 在美国语境下基本可互换，但 “cents” 更正式、更常用于书面语和金融语境；而 “pennies” 更口语化，也用于英国英语（英国的便士是 penny）。"
    },
    {
      "word_to_compare": "coins",
      "analysis": "“Coins” (硬币) 是一个更广泛的类别，包括所有金属货币，如镍币、角币、美元硬币等。而 “pennies” 仅特指最小面值的硬币。使用 “coins” 时不一定指小额，但 “pennies” 总是暗示低价值。"
    },
    {
      "word_to_compare": "dimes",
      "analysis": "“Dimes” 是美国的十分硬币，价值是 penny 的十倍。虽然两者都是硬币，但 “dimes” 代表的是相对较大的小额金额，而 “pennies” 强调极小、几乎可忽略的价值。在比喻中，说 ‘not worth a dime’ 意为毫无价值，而 ‘not worth a penny’ 更显穷困潦倒。"
    }
  ]
}