{
  "word": "prevalent",
  "pronunciation": "prev·uh·lent",
  "concise_definition": "adj. 普遍的, 流行的, 广泛存在的",
  "forms": {
    "comparative": "more prevalent",
    "superlative": "most prevalent"
  },
  "definitions": [
    {
      "pos": "adjective",
      "explanation_en": "Widespread or common in a particular area or at a particular time; occurring frequently or in large numbers.",
      "explanation_cn": "在特定地区或特定时期内广泛存在或常见的；频繁发生或数量众多。",
      "example_en": "Smoking was once prevalent among teenagers, but rates have dropped significantly in recent years.",
      "example_cn": "吸烟曾一度在青少年中很普遍，但近年来比例已大幅下降。"
    },
    {
      "pos": "adjective",
      "explanation_en": "Dominant or prevailing in influence, opinion, or practice, often to the exclusion of alternatives.",
      "explanation_cn": "在影响、观点或实践中占主导地位的，通常排斥其他替代方案。",
      "example_en": "The prevalent belief in the community is that education is the key to economic success.",
      "example_cn": "社区中普遍持有的信念是，教育是经济成功的关键。"
    }
  ],
  "comparison": [
    {
      "word_to_compare": "common",
      "analysis": "“Common” (常见的) 强调某事物出现频率高，但不一定具有广泛性或主导性，常用于日常语境。而 “prevalent” 更强调在特定群体、地区或时期内占据主导地位或普遍流行，语义更正式、范围更广。"
    },
    {
      "word_to_compare": "widespread",
      "analysis": "“Widespread” (广泛的) 侧重于地理或空间上的分布范围广，强调“覆盖区域大”。而 “prevalent” 更强调在特定语境中被广泛接受、流行或普遍存在，不一定涉及地理分布，更侧重于社会、文化或观念层面的普及。"
    },
    {
      "word_to_compare": "popular",
      "analysis": "“Popular” (受欢迎的) 强调受人喜爱或欢迎的程度，带有主观情感色彩。而 “prevalent” 是中性描述，仅说明某事物普遍存在或占主导，不涉及是否被喜爱。例如，某种错误观念可能很 prevalent，但并不 popular。"
    }
  ]
}