{
  "word": "resort",
  "pronunciation": "ri·zort",
  "concise_definition": "n. 度假胜地, 手段, 妥协; v. 诉诸, 依靠",
  "forms": {
    "third_person_singular": "resorts",
    "past_tense": "resorted",
    "past_participle": "resorted",
    "present_participle": "resorting"
  },
  "definitions": [
    {
      "pos": "noun",
      "explanation_en": "A place, especially one with natural attractions or facilities, that people visit for leisure, relaxation, or recreation, often during holidays.",
      "explanation_cn": "指一个具有自然风光或休闲设施、人们常在假期前往放松和娱乐的地方，如海滨度假村或滑雪胜地。",
      "example_en": "The Maldives is a popular resort destination for honeymooners.",
      "example_cn": "马尔代夫是蜜月旅行者喜爱的度假胜地。"
    },
    {
      "pos": "noun",
      "explanation_en": "A means or course of action taken when no other options are available, often reluctantly or as a last option.",
      "explanation_cn": "指在别无选择时所采取的手段或办法，通常带有无奈或最后手段的意味。",
      "example_en": "In times of crisis, many governments resort to emergency powers.",
      "example_cn": "在危机时期，许多政府不得不诉诸紧急权力。"
    },
    {
      "pos": "verb",
      "explanation_en": "To turn to or rely on something, especially as a last option or in desperation, often when other methods have failed.",
      "explanation_cn": "指在其他方法失效或陷入困境时，被迫依赖或求助于某种手段或方式。",
      "example_en": "She resorted to begging after losing her job.",
      "example_cn": "她失业后只好靠乞讨为生。"
    }
  ],
  "comparison": [
    {
      "word_to_compare": "destination",
      "analysis": "“Destination”（目的地）泛指任何旅行的终点，可以是城市、景点或国家，不强调休闲或度假功能。而 “resort” 特指提供休闲设施、专为度假设计的目的地，如酒店、海滩俱乐部等，具有更强的消费和服务属性。"
    },
    {
      "word_to_compare": "option",
      "analysis": "“Option”（选项）指在多个可能性中可自由选择的一种，中性且无情感色彩。而 “resort” 作为名词表示“手段”时，隐含着无奈、被动或最后的选择，带有负面或勉强的语义色彩。"
    },
    {
      "word_to_compare": "refuge",
      "analysis": "“Refuge”（避难所）强调为逃避危险、迫害或痛苦而寻求的安全庇护，具有强烈的生存或保护意味。而 “resort” 作为手段时，不一定涉及人身安全，更多是策略性或功能性依赖，语义范围更广、更中性。"
    }
  ]
}