{
  "word": "roommate",
  "pronunciation": "roo·meyt",
  "concise_definition": "n. 同屋者, 合租室友",
  "forms": {
    "plural": "roommates"
  },
  "definitions": [
    {
      "pos": "noun",
      "explanation_en": "A person who shares a room or living space with another person, typically in a dormitory, apartment, or house, often for practical or financial reasons.",
      "explanation_cn": "指与他人共同居住在同一房间或生活空间的人，通常出于实际或经济原因，如住在宿舍、公寓或房屋中。",
      "example_en": "My roommate and I split the rent and grocery bills equally.",
      "example_cn": "我和我的室友平分房租和杂货账单。"
    },
    {
      "pos": "noun",
      "explanation_en": "A person with whom one shares daily domestic life, including habits, routines, and sometimes conflicts, in a shared living environment.",
      "explanation_cn": "指在共同生活环境中与自己共享日常生活、习惯、作息，有时也包括矛盾与摩擦的人。",
      "example_en": "Even though we have different schedules, my roommate is surprisingly considerate.",
      "example_cn": "尽管我们的作息不同，我的室友却出乎意料地体贴。"
    }
  ],
  "comparison": [
    {
      "word_to_compare": "housemate",
      "analysis": "“Housemate”（同屋者）泛指与自己住在同一栋房屋中的任何人，无论是否共用房间，可能包括多个房间的合租者。而 “roommate” 更具体，特指共用一个房间的人，因此范围更窄、更精确。"
    },
    {
      "word_to_compare": "tenant",
      "analysis": "“Tenant”（租户）指租赁房屋或房间的法律主体，强调与房东之间的合同关系，不涉及是否与他人共享空间。而 “roommate” 强调的是共同生活的个人关系，不一定是法律意义上的租客（例如学生与学校宿舍）。"
    },
    {
      "word_to_compare": "flatmate",
      "analysis": "“Flatmate” 是英式英语中与 “roommate” 相近的词，但通常指与自己合租一套公寓（flat）的人，不一定共用卧室。在美式英语中，人们更常用 “roommate” 来涵盖所有合租情况，而 “flatmate” 则较少使用。"
    }
  ]
}