{
  "word": "sealed",
  "pronunciation": "seeld",
  "concise_definition": "adj. 密封的, 封闭的, 保密的",
  "forms": {
    "base_form": "seal",
    "past_tense": "sealed",
    "past_participle": "sealed",
    "present_participle": "sealing"
  },
  "definitions": [
    {
      "pos": "adjective",
      "explanation_en": "Closed or secured tightly so that nothing can enter or escape, often using a material like wax, adhesive, or a mechanical closure.",
      "explanation_cn": "通过蜡、粘合剂或机械装置紧密封闭，使任何物质都无法进入或逸出的状态。",
      "example_en": "The letter was sealed with red wax and bore the family crest.",
      "example_cn": "这封信用红色蜡封缄，并印有家族徽章。"
    },
    {
      "pos": "adjective",
      "explanation_en": "Legally or officially closed off, especially to prevent access or disclosure, such as a court record or contract.",
      "explanation_cn": "法律或官方意义上被封闭，通常为防止访问或披露，如法院记录或合同。",
      "example_en": "The investigation files were sealed by the judge to protect the privacy of the minors involved.",
      "example_cn": "法官为保护涉案未成年人的隐私，将调查文件封存。"
    },
    {
      "pos": "adjective",
      "explanation_en": "Firmly fixed or established, especially in a way that cannot be changed or reversed.",
      "explanation_cn": "牢固确立或固定，通常指无法更改或逆转的状态。",
      "example_en": "The deal was sealed with a handshake, and no further negotiations were allowed.",
      "example_cn": "交易以握手达成，此后不允许再进行任何谈判。"
    }
  ],
  "comparison": [
    {
      "word_to_compare": "closed",
      "analysis": "“Closed”（关闭的）是一个通用词，泛指任何不再开放的状态，如门、窗、商店等，不强调密封性或不可逆性。而 “sealed” 暗示更严格的封闭，通常涉及物理或法律上的防渗透、防篡改措施。"
    },
    {
      "word_to_compare": "locked",
      "analysis": "“Locked”（上锁的）特指通过钥匙、密码或机械装置防止进入，强调访问控制。而 “sealed” 更侧重于整体封闭，可能不涉及锁具，如蜡封、胶带封口，其目的可能是防泄漏、防篡改或保密，而非单纯防人进入。"
    },
    {
      "word_to_compare": "confidential",
      "analysis": "“Confidential”（机密的）强调信息的敏感性和保密性，但不一定有物理封闭。而 “sealed” 可以是物理封闭（如密封文件），也可以是法律意义上的保密状态（如密封档案），它更强调形式上的不可接触性，而不仅仅是内容的敏感性。"
    }
  ]
}