{
  "word": "supported",
  "pronunciation": "suh·pawr·tuhd",
  "concise_definition": "adj. 被支持的, 被资助的, 被拥护的",
  "forms": {
    "base_form": "support",
    "present_participle": "supporting",
    "past_tense": "supported",
    "past_participle": "supported"
  },
  "definitions": [
    {
      "pos": "adjective",
      "explanation_en": "Having received approval, assistance, or encouragement from a person, group, or system; often implying endorsement or financial backing.",
      "explanation_cn": "指获得了某人、团体或系统的认可、帮助或鼓励；通常暗示着支持、背书或资金资助。",
      "example_en": "The project is supported by a major university and several private donors.",
      "example_cn": "该项目得到了一所重点大学和多位私人捐赠者的支持。"
    },
    {
      "pos": "adjective",
      "explanation_en": "In a state of being upheld or maintained, especially in a physical, emotional, or ideological context.",
      "explanation_cn": "指在物理、情感或意识形态层面上被维持或支撑的状态。",
      "example_en": "She felt supported by her family during her difficult transition.",
      "example_cn": "在她艰难的转型期，她感受到家人的支持。"
    },
    {
      "pos": "adjective",
      "explanation_en": "In computing, referring to a system, device, or software that is compatible with or has the capability to work with a particular technology or standard.",
      "explanation_cn": "在计算机领域，指某个系统、设备或软件能够兼容或支持某种特定技术或标准。",
      "example_en": "This printer is supported by the latest version of macOS.",
      "example_cn": "这款打印机兼容最新的 macOS 版本。"
    }
  ],
  "comparison": [
    {
      "word_to_compare": "backed",
      "analysis": "“Backed” (有后盾的) 通常强调来自权威、资金或权力机构的强力支持，常用于政治、金融或商业语境，带有更强烈的保障意味。而 “supported” 更广泛，可涵盖情感、技术或道义上的支持，语气相对中性。"
    },
    {
      "word_to_compare": "endorsed",
      "analysis": "“Endorsed” (被背书的) 强调公开的、正式的赞同或推荐，常用于名人代言、品牌合作或政策声明，具有宣传和认证性质。而 “supported” 更侧重于实际的协助或维持，不一定包含公开表态。"
    },
    {
      "word_to_compare": "maintained",
      "analysis": "“Maintained” (被维持的) 强调持续性的保持或 upkeep，多用于物理状态（如设备维护）或系统运行，侧重于“不中断”而非“提供支持”。而 “supported” 更强调主动提供资源或力量以使某事物得以存在或运作。"
    }
  ]
}