{
  "word": "tended",
  "pronunciation": "ten·dɪd",
  "concise_definition": "v. 照料, 照顾, 倾向于（tend 的过去式和过去分词）",
  "forms": {
    "base_form": "tend",
    "third_person_singular": "tends",
    "present_participle": "tending",
    "past_tense": "tended",
    "past_participle": "tended"
  },
  "definitions": [
    {
      "pos": "verb",
      "explanation_en": "To care for or look after someone or something regularly, especially to ensure their health, growth, or proper condition.",
      "explanation_cn": "指定期照料或看护某人或某物，尤其是为了确保其健康、成长或良好状态。",
      "example_en": "She tended the garden every morning before work.",
      "example_cn": "她每天上班前都会照料花园。"
    },
    {
      "pos": "verb",
      "explanation_en": "To have a tendency or inclination toward a particular behavior, condition, or outcome, often observed in the past.",
      "explanation_cn": "指在过去表现出某种倾向、偏好或趋势，常用于描述习惯性行为或自然倾向。",
      "example_en": "He tended to arrive late for meetings.",
      "example_cn": "他过去常常开会迟到。"
    },
    {
      "pos": "verb",
      "explanation_en": "To attend to or manage a process or task, especially in a careful or attentive way.",
      "explanation_cn": "指细心地处理或管理某项事务或过程。",
      "example_en": "The nurse tended to the patient’s wounds with great care.",
      "example_cn": "护士非常小心地为病人处理伤口。"
    }
  ],
  "comparison": [
    {
      "word_to_compare": "care for",
      "analysis": "“Care for” 强调情感上的关心与呵护，常用于人或宠物，带有温情色彩；而 “tended” 更侧重于实际的、持续性的照料行为，可应用于人、植物、机器等，语义更中性、更偏重动作本身。"
    },
    {
      "word_to_compare": "inclined",
      "analysis": "“Inclined” 是形容词，表示主观上的倾向或偏好，常与 “to do” 搭配；而 “tended” 是动词的过去式，描述的是过去实际发生的倾向性行为，具有时间性和行为记录性，语义更具体、更客观。"
    },
    {
      "word_to_compare": "attended",
      "analysis": "“Attended” 强调“出席”或“在场服务”，如 attend a meeting 或 attend a patient（在旁看护），但不一定包含持续照料的含义；而 “tended” 更强调主动、持续、有目的的护理或管理行为，语义范围更广、动作性更强。"
    }
  ]
}