{
  "word": "tobias",
  "pronunciation": "tuh·bee·us",
  "concise_definition": "n. 托拜厄斯（男性名）",
  "forms": {
    "none": "无复数或变体形式"
  },
  "definitions": [
    {
      "pos": "noun",
      "explanation_en": "A male given name of Hebrew origin, meaning 'God is good' or 'the goodness of God'. It is used across various cultures and languages, often associated with religious or historical contexts.",
      "explanation_cn": "源自希伯来语的男性名字，意为‘上帝是良善的’或‘上帝的恩惠’。该名字在多种文化和语言中使用，常与宗教或历史背景相关。",
      "example_en": "Tobias was known for his kindness and unwavering faith in difficult times.",
      "example_cn": "托拜厄斯在困难时期以他的仁慈和坚定的信仰而闻名。"
    }
  ],
  "comparison": []
}